timegan/README.md
timegan/__init__.py
timegan/data/__init__.py
timegan/data/energy_data.csv
timegan/data/stock_data.csv
timegan/data_loading.py
timegan/foo.py
timegan/main_timegan.py
timegan/metrics/__init__.py
timegan/metrics/discriminative_metrics.py
timegan/metrics/predictive_metrics.py
timegan/metrics/visualization_metrics.py
timegan/requirements.txt
timegan/test.py
timegan/timegan.py
timegan/timegan_static.py
timegan/tutorial_timegan.ipynb
timegan/utils.py
timegan-0.1.11.dist-info/LICENSE.md
timegan-0.1.11.dist-info/METADATA
timegan-0.1.11.dist-info/WHEEL
timegan-0.1.11.dist-info/entry_points.txt
timegan-0.1.11.dist-info/RECORD
