Metadata-Version: 2.3
Name: timegan
Version: 0.1.11
Summary: A fork of https://github.com/jsyoon0823/TimeGAN that implements static features and snapshotting
Author: Zack Kromer
Author-email: fzachary.kromer@ucdenver.edu
Requires-Python: >=3.9,<3.12
Classifier: Programming Language :: Python :: 3
Classifier: Programming Language :: Python :: 3.9
Classifier: Programming Language :: Python :: 3.10
Classifier: Programming Language :: Python :: 3.11
Requires-Dist: matplotlib (>=3.1.1,<4.0.0)
Requires-Dist: numpy (==1.26.4)
Requires-Dist: scikit-learn (>=1.4.2,<2.0.0)
Requires-Dist: tensorflow (==2.11.0)
Requires-Dist: tf-slim
Requires-Dist: utils
Project-URL: Documentation, https://det-lab.github.io/TimeGAN-Static/
Project-URL: Repository, https://github.com/det-lab/TimeGAN-Static
